odoo/addons/artiga/__init__.py
odoo/addons/artiga/__manifest__.py
odoo/addons/artiga/static/src/xml/pos.xml
odoo12_addon_artiga-12.0.1.0.0.dist-info/METADATA
odoo12_addon_artiga-12.0.1.0.0.dist-info/WHEEL
odoo12_addon_artiga-12.0.1.0.0.dist-info/top_level.txt
odoo12_addon_artiga-12.0.1.0.0.dist-info/RECORD
